{
  "elapsedTime": 0,
  "status": "OK",
  "errors": [],
  "message": "",
  "timestamp": "2021-09-10 10:10:00",
  "bodyType": "ARRAY",
  "body":
  [
    {
      "patientAmt": "9260",
      "fullPatientAmt": "0",
      "selectMedicalAmt": "0",
      "totalAmt": "18520",
      "accumulatedLclsCd": "01",
      "insureAmt": "9260",
      "mainSubCd": null,
      "exceptSelectMedicalAmt": "0",
      "accumulatedLclsNm": "진찰료"
    },
    {
      "patientAmt": "0",
      "fullPatientAmt": "0",
      "selectMedicalAmt": "0",
      "totalAmt": "0",
      "accumulatedLclsCd": "02",
      "insureAmt": "0",
      "mainSubCd": null,
      "exceptSelectMedicalAmt": "0",
      "accumulatedLclsNm": "입원료(4인실이상)"
    },
    {
      "patientAmt": "0",
      "fullPatientAmt": "0",
      "selectMedicalAmt": "0",
      "totalAmt": "0",
      "accumulatedLclsCd": "03",
      "insureAmt": "0",
      "mainSubCd": null,
      "exceptSelectMedicalAmt": "0",
      "accumulatedLclsNm": "식대"
    },
    {
      "patientAmt": "25",
      "fullPatientAmt": "0",
      "selectMedicalAmt": "0",
      "totalAmt": "50",
      "accumulatedLclsCd": "04",
      "insureAmt": "25",
      "mainSubCd": null,
      "exceptSelectMedicalAmt": "0",
      "accumulatedLclsNm": "투약및조제료(행위료)"
    },
    {
      "patientAmt": "0",
      "fullPatientAmt": "0",
      "selectMedicalAmt": "0",
      "totalAmt": "24",
      "accumulatedLclsCd": "05",
      "insureAmt": "24",
      "mainSubCd": null,
      "exceptSelectMedicalAmt": "0",
      "accumulatedLclsNm": "투약및조제료(약품비)"
    },
    {
      "patientAmt": "2457",
      "fullPatientAmt": "0",
      "selectMedicalAmt": "0",
      "totalAmt": "4913",
      "accumulatedLclsCd": "06",
      "insureAmt": "2456",
      "mainSubCd": null,
      "exceptSelectMedicalAmt": "0",
      "accumulatedLclsNm": "주사료(행위료)"
    },
    {
      "patientAmt": "1392",
      "fullPatientAmt": "0",
      "selectMedicalAmt": "0",
      "totalAmt": "2783",
      "accumulatedLclsCd": "07",
      "insureAmt": "1391",
      "mainSubCd": null,
      "exceptSelectMedicalAmt": "0",
      "accumulatedLclsNm": "주사료(약품비)"
    },
    {
      "patientAmt": "0",
      "fullPatientAmt": "0",
      "selectMedicalAmt": "0",
      "totalAmt": "0",
      "accumulatedLclsCd": "08",
      "insureAmt": "0",
      "mainSubCd": null,
      "exceptSelectMedicalAmt": "0",
      "accumulatedLclsNm": "마취료"
    },
    {
      "patientAmt": "0",
      "fullPatientAmt": "0",
      "selectMedicalAmt": "0",
      "totalAmt": "0",
      "accumulatedLclsCd": "09",
      "insureAmt": "0",
      "mainSubCd": null,
      "exceptSelectMedicalAmt": "0",
      "accumulatedLclsNm": "처치및수술료"
    },
    {
      "patientAmt": "37133",
      "fullPatientAmt": "0",
      "selectMedicalAmt": "0",
      "totalAmt": "74263",
      "accumulatedLclsCd": "10",
      "insureAmt": "37130",
      "mainSubCd": null,
      "exceptSelectMedicalAmt": "0",
      "accumulatedLclsNm": "검사료"
    },
    {
      "patientAmt": "6098",
      "fullPatientAmt": "0",
      "selectMedicalAmt": "0",
      "totalAmt": "12195",
      "accumulatedLclsCd": "11",
      "insureAmt": "6097",
      "mainSubCd": null,
      "exceptSelectMedicalAmt": "0",
      "accumulatedLclsNm": "영상진단료"
    },
    {
      "patientAmt": "0",
      "fullPatientAmt": "0",
      "selectMedicalAmt": "0",
      "totalAmt": "0",
      "accumulatedLclsCd": "12",
      "insureAmt": "0",
      "mainSubCd": null,
      "exceptSelectMedicalAmt": "0",
      "accumulatedLclsNm": "방사선치료료"
    },
    {
      "patientAmt": "112",
      "fullPatientAmt": "0",
      "selectMedicalAmt": "0",
      "totalAmt": "140",
      "accumulatedLclsCd": "13",
      "insureAmt": "28",
      "mainSubCd": null,
      "exceptSelectMedicalAmt": "0",
      "accumulatedLclsNm": "치료재료대"
    },
    {
      "patientAmt": "0",
      "fullPatientAmt": "0",
      "selectMedicalAmt": "0",
      "totalAmt": "0",
      "accumulatedLclsCd": "14",
      "insureAmt": "0",
      "mainSubCd": null,
      "exceptSelectMedicalAmt": "0",
      "accumulatedLclsNm": "재활및물리치료료"
    },
    {
      "patientAmt": "0",
      "fullPatientAmt": "0",
      "selectMedicalAmt": "0",
      "totalAmt": "0",
      "accumulatedLclsCd": "15",
      "insureAmt": "0",
      "mainSubCd": null,
      "exceptSelectMedicalAmt": "0",
      "accumulatedLclsNm": "정신요법료"
    },
    {
      "patientAmt": "0",
      "fullPatientAmt": "0",
      "selectMedicalAmt": "0",
      "totalAmt": "0",
      "accumulatedLclsCd": "16",
      "insureAmt": "0",
      "mainSubCd": null,
      "exceptSelectMedicalAmt": "0",
      "accumulatedLclsNm": "전혈및혈액성분제제료"
    },
    {
      "patientAmt": "0",
      "fullPatientAmt": "0",
      "selectMedicalAmt": "0",
      "totalAmt": "0",
      "accumulatedLclsCd": "17",
      "insureAmt": "0",
      "mainSubCd": null,
      "exceptSelectMedicalAmt": "0",
      "accumulatedLclsNm": "예약진찰료"
    },
    {
      "patientAmt": "0",
      "fullPatientAmt": "0",
      "selectMedicalAmt": "0",
      "totalAmt": "0",
      "accumulatedLclsCd": "18",
      "insureAmt": "0",
      "mainSubCd": null,
      "exceptSelectMedicalAmt": "0",
      "accumulatedLclsNm": "응급의학관리료"
    },
    {
      "patientAmt": "0",
      "fullPatientAmt": "0",
      "selectMedicalAmt": "0",
      "totalAmt": "0",
      "accumulatedLclsCd": "19",
      "insureAmt": "0",
      "mainSubCd": null,
      "exceptSelectMedicalAmt": "0",
      "accumulatedLclsNm": "CT진단료"
    },
    {
      "patientAmt": "0",
      "fullPatientAmt": "0",
      "selectMedicalAmt": "0",
      "totalAmt": "0",
      "accumulatedLclsCd": "20",
      "insureAmt": "0",
      "mainSubCd": null,
      "exceptSelectMedicalAmt": "0",
      "accumulatedLclsNm": "MRI진단료"
    },
    {
      "patientAmt": "0",
      "fullPatientAmt": "0",
      "selectMedicalAmt": "0",
      "totalAmt": "0",
      "accumulatedLclsCd": "21",
      "insureAmt": "0",
      "mainSubCd": null,
      "exceptSelectMedicalAmt": "0",
      "accumulatedLclsNm": "PET진단료"
    },
    {
      "patientAmt": "0",
      "fullPatientAmt": "0",
      "selectMedicalAmt": "0",
      "totalAmt": "0",
      "accumulatedLclsCd": "22",
      "insureAmt": "0",
      "mainSubCd": null,
      "exceptSelectMedicalAmt": "0",
      "accumulatedLclsNm": "초음파진단료"
    },
    {
      "patientAmt": "0",
      "fullPatientAmt": "0",
      "selectMedicalAmt": "0",
      "totalAmt": "0",
      "accumulatedLclsCd": "23",
      "insureAmt": "0",
      "mainSubCd": null,
      "exceptSelectMedicalAmt": "0",
      "accumulatedLclsNm": "보철/교정료"
    },
    {
      "patientAmt": "0",
      "fullPatientAmt": "0",
      "selectMedicalAmt": "0",
      "totalAmt": "0",
      "accumulatedLclsCd": "24",
      "insureAmt": "0",
      "mainSubCd": null,
      "exceptSelectMedicalAmt": "0",
      "accumulatedLclsNm": "병실차액"
    },
    {
      "patientAmt": "0",
      "fullPatientAmt": "0",
      "selectMedicalAmt": "0",
      "totalAmt": "0",
      "accumulatedLclsCd": "25",
      "insureAmt": "0",
      "mainSubCd": null,
      "exceptSelectMedicalAmt": "0",
      "accumulatedLclsNm": "제증명및기타"
    },
    {
      "patientAmt": "0",
      "fullPatientAmt": "0",
      "selectMedicalAmt": "0",
      "totalAmt": "0",
      "accumulatedLclsCd": "26",
      "insureAmt": "0",
      "mainSubCd": null,
      "exceptSelectMedicalAmt": "0",
      "accumulatedLclsNm": "포괄수가진료비"
    },
    {
      "patientAmt": "0",
      "fullPatientAmt": "0",
      "selectMedicalAmt": "0",
      "totalAmt": "0",
      "accumulatedLclsCd": "28",
      "insureAmt": "0",
      "mainSubCd": null,
      "exceptSelectMedicalAmt": "0",
      "accumulatedLclsNm": "선별급여"
    },
    {
      "patientAmt": "1355",
      "fullPatientAmt": "0",
      "selectMedicalAmt": "0",
      "totalAmt": "2710",
      "accumulatedLclsCd": "29",
      "insureAmt": "1355",
      "mainSubCd": null,
      "exceptSelectMedicalAmt": "0",
      "accumulatedLclsNm": "관리료"
    },
    {
      "patientAmt": "0",
      "fullPatientAmt": "0",
      "selectMedicalAmt": "0",
      "totalAmt": "0",
      "accumulatedLclsCd": "30",
      "insureAmt": "0",
      "mainSubCd": null,
      "exceptSelectMedicalAmt": "0",
      "accumulatedLclsNm": "입원료(1인실)"
    },
    {
      "patientAmt": "0",
      "fullPatientAmt": "0",
      "selectMedicalAmt": "0",
      "totalAmt": "0",
      "accumulatedLclsCd": "31",
      "insureAmt": "0",
      "mainSubCd": null,
      "exceptSelectMedicalAmt": "0",
      "accumulatedLclsNm": "입원료(2-3인실)"
    }
  ]
}
