{"elapsedTime":1,"status":"OK","errors":[],"message":"","timestamp":"2019-01-23 19:54:46","bodyType":"ARRAY","body":[
  {
    "billPrtYn": null,
    "calculationYn": null,
    "deptNm": null,
    "discountAmt": null,
    "discountCd": null,
    "doctorNm": null,
    "insPattype": null,
    "insTypeCd": null,
    "insuranceCd": null,
    "insureAmt": null,
    "partChargeYn": null,
    "patientAmt": null,
    "patientTotalAmt": null,
    "preAmt": null,
    "prescriptionInCnt": null,
    "prescriptionOut": null,
    "prescriptionOutCnt": null,
    "realAmt": null,
    "receiptAmt": "0",
    "receiptDt": null,
    "receiptNo": null,
    "receiptSeq": "0",
    "receiptTm": null,
    "receivableAmt": null,
    "reservationAmt": null,
    "returnCd": "0001",
    "returnMsg": "오늘 진료하신 내역이 없습니다.(03)",
    "subInsuranceCd": null,
    "surtax": null,
    "totalAmt": null,
    "totalNonPayment": null,
    "totalPayment": null,
    "transactionId": null
  }
]}
