{
  "elapsedTime": 0,
  "status": "OK",
  "errors": [],
  "message": "",
  "timestamp": "2020-10-16 11:26:00",
  "bodyType": "ARRAY",
  "body": [
    {
      "mdrpNo": 1759098,
      "mcdpCd": "NP",
      "discountAmt": 0,
      "pvicAmt": 0,
      "txtnAmt": 0,
      "patientId": "01658474",
      "wardNm": "동관7층",
      "totlClrsAmt": 0,
      "rcpcAmt": 456880,
      "disabledFund": 0,
      "contribution": 0,
      "totalPayment": 0,
      "rareSupportfund": 0,
      "intermediateAmt": 10000,
      "receiptAmt": 456880,
      "errYn": "N",
      "patientAmt": 0,
      "wardCd": "A07",
      "patientNm": "정*_T",
      "roomNm": "11",
      "mcrcYmd": "20230207",
      "mcdpNm": "정신건강의학과",
      "flatRateDiffer": 0,
      "bloodAmt": 0,
      "customerAmt": 0,
      "clamAmt": 0,
      "preAmt": 0,
      "selectMedicalAmt": 0,
      "totalAmt": 466880,
      "intermediatePayStDt": "20230207",
      "istyNm": "일반",
      "intermediatePayEndDt": "20230209",
      "unacceptableRmk": null,
      "upperLmtExcdAmt": 0,
      "mdcrYmd": "202302071114",
      "totalNonPayment": 466880
    }
  ]
}